gpumap/__init__.py
gpumap/compute_membership_strengths_gpu.py
gpumap/distances.py
gpumap/gpumap_.py
gpumap/nearest_neighbors_gpu.py
gpumap/nndescent.py
gpumap/optimize_layout_gpu.py
gpumap/rp_tree.py
gpumap/rp_tree_gpu.py
gpumap/smooth_knn_dist_gpu.py
gpumap/sparse.py
gpumap/spectral.py
gpumap/spectral_gpu.py
gpumap/utils.py
gpumap/validation.py
gpumap-0.1.1.dist-info/LICENSE.txt
gpumap-0.1.1.dist-info/METADATA
gpumap-0.1.1.dist-info/WHEEL
gpumap-0.1.1.dist-info/top_level.txt
gpumap-0.1.1.dist-info/RECORD
