Metadata-Version: 2.1
Name: gpumap
Version: 0.1.1
Summary: UMAP with GPUs
Home-page: http://github.com/p3732/gpumap
Maintainer: Peter Eisenmann
Maintainer-email: p3732@gmx.de
License: BSD
Keywords: dimension reduction t-sne manifold umap
Platform: UNKNOWN
Classifier: Development Status :: 3 - Alpha
Classifier: Intended Audience :: Science/Research
Classifier: Intended Audience :: Developers
Classifier: License :: OSI Approved
Classifier: Programming Language :: C
Classifier: Programming Language :: Python
Classifier: Topic :: Software Development
Classifier: Topic :: Scientific/Engineering
Classifier: Operating System :: POSIX
Classifier: Operating System :: Unix
Classifier: Operating System :: MacOS
Classifier: Programming Language :: Python :: 3.7
Requires-Dist: numpy (>=1.13)
Requires-Dist: scikit-learn (>=0.16)
Requires-Dist: scipy (>=0.19)
Requires-Dist: numba (>=0.37)
Requires-Dist: faiss (>=1.5.3)
Requires-Dist: cupy (>=6.0.0)
